README.rst
setup.py
BinanceWatch/BinanceManager.py
BinanceWatch/__init__.py
BinanceWatch.egg-info/PKG-INFO
BinanceWatch.egg-info/SOURCES.txt
BinanceWatch.egg-info/dependency_links.txt
BinanceWatch.egg-info/requires.txt
BinanceWatch.egg-info/top_level.txt
BinanceWatch/storage/BinanceDataBase.py
BinanceWatch/storage/DataBase.py
BinanceWatch/storage/__init__.py
BinanceWatch/storage/tables.py
BinanceWatch/utils/LoggerGenerator.py
BinanceWatch/utils/__init__.py
BinanceWatch/utils/manage.py
BinanceWatch/utils/paths.py
BinanceWatch/utils/time_utils.py
tests/__init__.py
tests/__main__.py
tests/print_utils.py
tests/test_DataBase.py