Metadata-Version: 2.1
Name: BinanceWatch
Version: 0.1.3
Summary: Local tracker of a binance account
Home-page: https://github.com/EtWnn/BinanceWatch
Author: EtWnn
Author-email: 
License: MIT
Keywords: binance exchange wallet save tracking history bitcoin ethereum btc eth
Platform: UNKNOWN
Classifier: Intended Audience :: Developers
Classifier: License :: OSI Approved :: MIT License
Classifier: Operating System :: OS Independent
Classifier: Programming Language :: Python :: 3.7
Classifier: Programming Language :: Python
Classifier: Topic :: Software Development :: Libraries :: Python Modules
